{"chunk_definitions":[{"chunk_id":"c24iltkhoupzd","chunk_label":"Load tidyverse","document_id":"D8DB73E2","expansion_state":0,"options":{"engine":"r","label":"Load tidyverse, gapminder, knitr"},"row":18,"row_count":1,"visible":true},{"chunk_id":"c0kpns5la56vp","chunk_label":"unnamed-chunk-1","document_id":"D8DB73E2","expansion_state":0,"options":{"engine":"r","label":"unnamed-chunk-16"},"row":29,"row_count":1,"visible":true},{"chunk_id":"cs2m387q3bjp1","chunk_label":"unnamed-chunk-2","document_id":"D8DB73E2","expansion_state":0,"options":{"engine":"r","label":"unnamed-chunk-21"},"row":42,"row_count":1,"visible":true},{"chunk_id":"ca7rbhiykm36a","chunk_label":"unnamed-chunk-3","document_id":"D8DB73E2","expansion_state":0,"options":{"engine":"r","label":"unnamed-chunk-26"},"row":52,"row_count":1,"visible":true}],"doc_write_time":1539733354}