{"chunk_definitions":[{"chunk_id":"cz0l9jth4dqs5","chunk_label":"Load tidyverse","document_id":"D8DB73E2","expansion_state":0,"options":{"engine":"r","label":"Load tidyverse, gapminder, knitr"},"row":30,"row_count":1,"visible":true},{"chunk_id":"cc1mmscig9u0b","chunk_label":"unnamed-chunk-1","document_id":"D8DB73E2","expansion_state":0,"options":{"engine":"r","label":"unnamed-chunk-1"},"row":44,"row_count":1,"visible":true},{"chunk_id":"chzmuuuyailb7","chunk_label":"unnamed-chunk-2","document_id":"D8DB73E2","expansion_state":0,"options":{"engine":"r","label":"unnamed-chunk-2"},"row":51,"row_count":1,"visible":true},{"chunk_id":"c2zmasm369pja","chunk_label":"unnamed-chunk-3","document_id":"D8DB73E2","expansion_state":0,"options":{"engine":"r","label":"unnamed-chunk-3"},"row":61,"row_count":1,"visible":true},{"chunk_id":"c4ng4cs1ezdjp","chunk_label":"unnamed-chunk-4","document_id":"D8DB73E2","expansion_state":0,"options":{"engine":"r","label":"unnamed-chunk-4"},"row":67,"row_count":1,"visible":true},{"chunk_id":"cpne1n9d1sq46","chunk_label":"unnamed-chunk-5","document_id":"D8DB73E2","expansion_state":0,"options":{"engine":"r","label":"unnamed-chunk-5"},"row":71,"row_count":1,"visible":true},{"chunk_id":"ckn2svt0rpkxc","chunk_label":"unnamed-chunk-6","document_id":"D8DB73E2","expansion_state":0,"options":{"engine":"r","label":"unnamed-chunk-6"},"row":75,"row_count":1,"visible":true},{"chunk_id":"c5skibn4ctmzc","chunk_label":"unnamed-chunk-7","document_id":"D8DB73E2","expansion_state":0,"options":{"engine":"r","label":"unnamed-chunk-7"},"row":83,"row_count":1,"visible":true},{"chunk_id":"c9o2xgikxh4y1","chunk_label":"unnamed-chunk-8","document_id":"D8DB73E2","expansion_state":0,"options":{"engine":"r","label":"unnamed-chunk-8"},"row":95,"row_count":1,"visible":true},{"chunk_id":"c77755trp1fis","chunk_label":"unnamed-chunk-9","document_id":"D8DB73E2","expansion_state":0,"options":{"engine":"r","label":"unnamed-chunk-9"},"row":104,"row_count":1,"visible":true},{"chunk_id":"c3156rkrnv0x3","chunk_label":"unnamed-chunk-10","document_id":"D8DB73E2","expansion_state":0,"options":{"engine":"r","label":"unnamed-chunk-10"},"row":112,"row_count":1,"visible":true},{"chunk_id":"c3zis4i4rzbab","chunk_label":"unnamed-chunk-11","document_id":"D8DB73E2","expansion_state":0,"options":{"engine":"r","label":"unnamed-chunk-11"},"row":124,"row_count":1,"visible":true},{"chunk_id":"c2daypi41bz7w","chunk_label":"unnamed-chunk-12","document_id":"D8DB73E2","expansion_state":0,"options":{"engine":"r","label":"unnamed-chunk-12"},"row":133,"row_count":1,"visible":true},{"chunk_id":"c575cdlg3l3k1","chunk_label":"unnamed-chunk-13","document_id":"D8DB73E2","expansion_state":0,"options":{"engine":"r","label":"unnamed-chunk-13"},"row":156,"row_count":1,"visible":true},{"chunk_id":"c1v7n8v0asqm9","chunk_label":"unnamed-chunk-14","document_id":"D8DB73E2","expansion_state":0,"options":{"engine":"r","label":"unnamed-chunk-14"},"row":179,"row_count":1,"visible":true},{"chunk_id":"cmpz6k0mcyk96","chunk_label":"unnamed-chunk-15","document_id":"D8DB73E2","expansion_state":0,"options":{"engine":"r","label":"unnamed-chunk-15"},"row":195,"row_count":1,"visible":true},{"chunk_id":"cvxtcmj1e7qfr","chunk_label":"unnamed-chunk-16","document_id":"D8DB73E2","expansion_state":0,"options":{"engine":"r","label":"unnamed-chunk-16"},"row":211,"row_count":1,"visible":true},{"chunk_id":"caxb2ii9v664y","chunk_label":"unnamed-chunk-17","document_id":"D8DB73E2","expansion_state":0,"options":{"engine":"r","label":"unnamed-chunk-17"},"row":225,"row_count":1,"visible":true},{"chunk_id":"cclsku1qcwnt1","chunk_label":"unnamed-chunk-18","document_id":"D8DB73E2","expansion_state":0,"options":{"engine":"r","label":"unnamed-chunk-18"},"row":241,"row_count":1,"visible":true},{"chunk_id":"c59f7l5mfhzja","chunk_label":"unnamed-chunk-19","document_id":"D8DB73E2","expansion_state":0,"options":{"engine":"r","label":"unnamed-chunk-19"},"row":249,"row_count":1,"visible":true},{"chunk_id":"ch9io6waysgpm","chunk_label":"unnamed-chunk-20","document_id":"D8DB73E2","expansion_state":0,"options":{"engine":"r","label":"unnamed-chunk-54"},"row":264,"row_count":1,"visible":true},{"chunk_id":"cfrq3bbaad5pv","chunk_label":"unnamed-chunk-21","document_id":"D8DB73E2","expansion_state":0,"options":{"engine":"r","label":"unnamed-chunk-20"},"row":271,"row_count":1,"visible":true},{"chunk_id":"cpizhzg9f47ge","chunk_label":"unnamed-chunk-22","document_id":"D8DB73E2","expansion_state":0,"options":{"engine":"r","label":"unnamed-chunk-22"},"row":278,"row_count":1,"visible":true}],"chunk_rendered_width":450,"doc_write_time":1539985893}